pipewire_python/__init__.py
pipewire_python/_constants.py
pipewire_python/_utils.py
pipewire_python/controller.py
pipewire_python/link.py
pipewire_python-0.2.3.dist-info/LICENSE
pipewire_python-0.2.3.dist-info/WHEEL
pipewire_python-0.2.3.dist-info/METADATA
pipewire_python-0.2.3.dist-info/RECORD
