Metadata-Version: 2.1
Name: pipewire_python
Version: 0.2.3
Summary: Python controller, player and recorder via pipewire's commands
Author: mrteathyme
Author-email: Pablo Diaz <pablo.diazv@pucp.edu.pe>, Anna Absi <anna.absi@gmail.com>, Joe Stanley <engineerjoe440@yahoo.com>
Maintainer-email: Pablo Diaz <pablo.diazv@pucp.edu.pe>
Requires-Python: >=3.7
Classifier: License :: OSI Approved :: MIT License
Classifier: Intended Audience :: Developers
Classifier: Intended Audience :: Science/Research
Classifier: Natural Language :: English
Classifier: Topic :: Multimedia :: Sound/Audio :: Capture/Recording
Classifier: Topic :: Multimedia :: Sound/Audio :: Players
Classifier: Programming Language :: Python :: 3.7
Classifier: Programming Language :: Python :: 3.8
Classifier: Programming Language :: Python :: 3.9
Classifier: Programming Language :: Python :: 3.10
Classifier: Programming Language :: Python :: 3.11
Project-URL: Documentation, https://pablodz.github.io/pipewire_python/html/pipewire_python.html
Project-URL: Home, https://github.com/pablodz/pipewire_python
